muswmm/__init__.py
muswmm/errors.py
muswmm/geometry.py
muswmm/namedobject.py
muswmm/namedobjects.py
muswmm/options.py
muswmm/output.py
muswmm/project.py
muswmm/simulator.py
muswmm/lib/Mumu.SWMM.Output.dll
muswmm/lib/Mumu.SWMM.SwmmObjects.dll
muswmm/lib/__init__.py
muswmm/lib/x64/__init__.py
muswmm/lib/x64/swmm51015.dll
muswmm/lib/x64/swmm52000.dll
muswmm/lib/x86/__init__.py
muswmm/lib/x86/swmm51015.dll
muswmm/lib/x86/swmm52000.dll
muswmm-0.1.1.dist-info/LICENSE
muswmm-0.1.1.dist-info/METADATA
muswmm-0.1.1.dist-info/WHEEL
muswmm-0.1.1.dist-info/top_level.txt
muswmm-0.1.1.dist-info/RECORD
