Metadata-Version: 2.1
Name: muswmm
Version: 0.1.1
Summary: muswmm是一个可以管理SWMM项目、设计SWMM模拟器、过程实时控制模拟的Python开发工具库。
Home-page: UNKNOWN
Author: Lei Zhang
Author-email: gemini.zhang@qq.com
License: MIT
Platform: UNKNOWN
License-File: LICENSE
